{
  "global": {
    "Transbank": {
      "300 Default": {
        "value": "#d5006c",
        "type": "color"
      }
    },
    "Surface": {
      "Interactive": {
        "Tbk": {
          "Active": {
            "value": "#d5006c",
            "type": "color"
          }
        }
      }
    },
    "Border": {
      "Interactive": {
        "Tbk": {
          "Active": {
            "value": "#d5006c",
            "type": "color"
          },
          "Disabled": {
            "value": "{Grey.200}",
            "type": "color"
          }
        }
      }
    },
    "Grey": {
      "200": {
        "value": "#888",
        "type": "color"
      }
    }
  },
  "$themes": []
}